DiscordBotsAPI/__init__.py
discord_bot_fr_api-1.0.0.dist-info/DESCRIPTION.rst
discord_bot_fr_api-1.0.0.dist-info/METADATA
discord_bot_fr_api-1.0.0.dist-info/RECORD
discord_bot_fr_api-1.0.0.dist-info/WHEEL
discord_bot_fr_api-1.0.0.dist-info/metadata.json
discord_bot_fr_api-1.0.0.dist-info/top_level.txt
