Metadata-Version: 2.0
Name: discord-bot-fr-api
Version: 1.0.0
Summary: Permet d'interagir avec l'API de DiscordBots-FR
Home-page: https://github.com/lapin-b/discord-bots-api-fr
Author: l4p1n
Author-email: contact@l4p1n.met-hardware.fr
License: LGPL-3.0
Project-URL: Bug reports, https://github.com/lapin-b/discord-bots-api-fr/issues
Project-URL: Source, https://github.com/lapin-b/discord-bots-api-fr
Keywords: discord bot api fr
Platform: UNKNOWN
Requires-Dist: requests
